resins/__init__.py
resins/instrument.py
resins/instrument_data/arcs.yaml
resins/instrument_data/cncs.yaml
resins/instrument_data/hyspec.yaml
resins/instrument_data/ideal.yaml
resins/instrument_data/lagrange.yaml
resins/instrument_data/let.yaml
resins/instrument_data/maps.yaml
resins/instrument_data/mari.yaml
resins/instrument_data/merlin.yaml
resins/instrument_data/panther.yaml
resins/instrument_data/sequoia.yaml
resins/instrument_data/tosca.yaml
resins/instrument_data/vision.yaml
resins/models/__init__.py
resins/models/ideal.py
resins/models/mixins.py
resins/models/model_base.py
resins/models/panther_abins.py
resins/models/polynomial.py
resins/models/pychop.py
resins/models/tosca_book.py
resins/models/vision_paper.py
resins-0.1.0.dist-info/licenses/LICENSE
resins-0.1.0.dist-info/METADATA
resins-0.1.0.dist-info/WHEEL
resins-0.1.0.dist-info/top_level.txt
resins-0.1.0.dist-info/RECORD
