Metadata-Version: 2.4
Name: resins
Version: 0.1.0
Summary: Python library for working with resolution functions of neutron instruments 
Author-email: Rastislav Turanyi <rastislav.turanyi@stfc.ac.uk>
Maintainer-email: Rastislav Turanyi <rastislav.turanyi@stfc.ac.uk>
License-Expression: GPL-3.0-or-later
Project-URL: Repository, https://github.com/pace-neutrons/resins
Keywords: Python,physics,inelastic neutron scattering,instrument resolution
Classifier: Development Status :: 3 - Alpha
Classifier: Intended Audience :: Developers
Classifier: Intended Audience :: Science/Research
Classifier: Programming Language :: Python
Classifier: Topic :: Scientific/Engineering :: Physics
Requires-Python: >=3.11
License-File: LICENSE
Requires-Dist: PyYAML>=6.0.2
Requires-Dist: numpy>=2.1.0
Requires-Dist: scipy>=1.13.1
Requires-Dist: typing_extensions>=4.5.0
Provides-Extra: dev
Requires-Dist: Pint>=0.24.3; extra == "dev"
Requires-Dist: jaxtyping>=0.2.34; extra == "dev"
Dynamic: license-file
